{
  "id": "confluence-a-simpler-way-to-invite-people-and-set-access-in-confluence",
  "title": "A simpler way to invite people and set access in Confluence",
  "product": "Confluence",
  "status": "rolling_out",
  "description": "Now, anyone can invite someone new or request access for them in Confluence and set their content permissions – all in one step. To invite someone and set their access: Open a content type in Confluence.\n\tSelect Share.\n\tEnter the email address of the person you want to invite or request access for.\n\tChoose the intended content permissions for them.\n\tSelect Share to complete the process.",
  "announced_date": "2026-03-09",
  "rollout_start_date": "2026-03-09",
  "rollout_end_date": "2026-03-09",
  "last_seen_week": "2026-03-23",
  "source_url": "https://confluence.atlassian.com/cloud/blog/2026/03/atlassian-cloud-changes-mar-9-to-mar-16-2026",
  "history": [
    {
      "date": "2026-03-09",
      "status": "rolling_out",
      "week_url": "https://confluence.atlassian.com/cloud/blog/2026/03/atlassian-cloud-changes-mar-9-to-mar-16-2026"
    },
    {
      "date": "2026-03-16",
      "status": "rollout_complete",
      "note": "Not seen in 4 consecutive weeks"
    },
    {
      "date": "2026-03-23",
      "status": "rolling_out",
      "week_url": "https://confluence.atlassian.com/cloud/blog/2026/03/atlassian-cloud-changes-mar-23-to-mar-30-2026"
    }
  ]
}