{
  "id": "jira-service-management-weve-made-looking-up-assets-objects-in-automation-easier",
  "title": "We’ve made looking up Assets objects in Automation easier",
  "product": "Jira Service Management",
  "status": "rollout_complete",
  "description": "You can now use filters to generate an AQL query when using the Lookup objects action in Automation. Simply select Basic to choose an object type plus any attributes, and an AQL query will be generated for you. This query will use attributes as placeholders for you to then customize with relevant smart values. The results of this query can also be used in other Automation actions using the lookupObjects smart value. Read more about using smart values for Assets.",
  "announced_date": "2025-12-01",
  "rollout_start_date": "2025-11-17",
  "rollout_end_date": "2025-12-01",
  "last_seen_week": "2025-12-01",
  "source_url": "https://confluence.atlassian.com/cloud/blog/2025/12/atlassian-cloud-changes-dec-1-to-dec-8-2025",
  "history": [
    {
      "date": "2025-12-01",
      "status": "released",
      "week_url": "https://confluence.atlassian.com/cloud/blog/2025/12/atlassian-cloud-changes-dec-1-to-dec-8-2025"
    },
    {
      "date": "2025-11-17",
      "status": "rolling_out",
      "week_url": "https://confluence.atlassian.com/cloud/blog/2025/11/atlassian-cloud-changes-nov-17-to-nov-24-2025"
    },
    {
      "date": "2026-01-26",
      "status": "rollout_complete",
      "note": "Not seen in 4 consecutive weeks"
    }
  ]
}