{
  "id": "jira-platform-delete-attachments-in-bulk",
  "title": "Delete attachments in bulk",
  "product": "Jira platform",
  "status": "coming_soon",
  "description": "Delete multiple attachments at once from the attachments panel in Jira. You can now delete multiple attachments on a work item at once. In the work item, select the attachments using the checkbox next to each item that you want to delete in bulk.\n\tConfirm that you want to delete these attachments.",
  "announced_date": "2026-03-09",
  "rollout_start_date": null,
  "rollout_end_date": null,
  "last_seen_week": "2026-03-09",
  "source_url": "https://confluence.atlassian.com/cloud/blog/2026/03/atlassian-cloud-changes-mar-9-to-mar-16-2026",
  "history": [
    {
      "date": "2026-03-09",
      "status": "coming_soon",
      "week_url": "https://confluence.atlassian.com/cloud/blog/2026/03/atlassian-cloud-changes-mar-9-to-mar-16-2026"
    }
  ]
}